LICENSE
README.md
pyproject.toml
custom_veomni.egg-info/PKG-INFO
custom_veomni.egg-info/SOURCES.txt
custom_veomni.egg-info/dependency_links.txt
custom_veomni.egg-info/requires.txt
custom_veomni.egg-info/top_level.txt
docs/conf.py
scripts/deepseek_v3/fp8_cast_bf16.py
scripts/deepseek_v3/kernel.py
scripts/moe_ckpt_merge/moe_merge.py
scripts/profile/merge_chrome_trace.py
tasks/omni/infer_omni_model.py
tasks/omni/infer_qwen2_vl.py
tasks/omni/train_flux.py
tasks/omni/train_omni_model.py
tasks/omni/train_qwen2_5_vl.py
tasks/omni/train_qwen2_vl.py
tasks/omni/train_wan.py
veomni/__init__.py
veomni/checkpoint/__init__.py
veomni/checkpoint/checkpointer.py
veomni/checkpoint/format_utils.py
veomni/data/__init__.py
veomni/data/batching_strategy.py
veomni/data/chat_template.py
veomni/data/constants.py
veomni/data/data_collator.py
veomni/data/data_loader.py
veomni/data/data_transform.py
veomni/data/dataset.py
veomni/data/dummy_dataset.py
veomni/data/dynamic_batching.py
veomni/data/diffusion/data_loader.py
veomni/data/diffusion/dataset.py
veomni/data/diffusion/preprocess/origin_dataset.py
veomni/data/multimodal/__init__.py
veomni/data/multimodal/audio_utils.py
veomni/data/multimodal/data_collator.py
veomni/data/multimodal/image_utils.py
veomni/data/multimodal/multimodal_chat_template.py
veomni/data/multimodal/multimodal_transform.py
veomni/data/multimodal/preprocess.py
veomni/data/multimodal/video_utils.py
veomni/distributed/__init__.py
veomni/distributed/checkpoint.py
veomni/distributed/offloading.py
veomni/distributed/parallel_plan.py
veomni/distributed/parallel_state.py
veomni/distributed/torch_parallelize.py
veomni/distributed/utils.py
veomni/distributed/vescale_parallelize.py
veomni/distributed/vescale_plan.py
veomni/distributed/fsdp/__init__.py
veomni/distributed/fsdp/clip_grad_norm.py
veomni/distributed/fsdp/extension.py
veomni/distributed/fsdp/initialize.py
veomni/distributed/fsdp2/__init__.py
veomni/distributed/fsdp2/clip_grad_norm.py
veomni/distributed/moe/__init__.py
veomni/distributed/moe/comm.py
veomni/distributed/moe/moe_layer.py
veomni/distributed/moe/moe_utils.py
veomni/distributed/sequence_parallel/__init__.py
